[
    {
        "frame": 0,
        "src_frame_idx": 0,
        "bbox": [
            536,
            116,
            161,
            223
        ],
        "left_eye": [
            580,
            208
        ],
        "right_eye": [
            657,
            209
        ]
    },
    {
        "frame": 1,
        "src_frame_idx": 30,
        "bbox": [
            538,
            118,
            164,
            223
        ],
        "left_eye": [
            581,
            204
        ],
        "right_eye": [
            660,
            202
        ]
    },
    {
        "frame": 2,
        "src_frame_idx": 60,
        "bbox": [
            531,
            127,
            163,
            223
        ],
        "left_eye": [
            573,
            212
        ],
        "right_eye": [
            652,
            205
        ]
    },
    {
        "frame": 3,
        "src_frame_idx": 90,
        "bbox": [
            538,
            115,
            160,
            221
        ],
        "left_eye": [
            578,
            200
        ],
        "right_eye": [
            657,
            193
        ]
    },
    {
        "frame": 4,
        "src_frame_idx": 120,
        "bbox": [
            535,
            112,
            163,
            216
        ],
        "left_eye": [
            577,
            200
        ],
        "right_eye": [
            656,
            193
        ]
    },
    {
        "frame": 5,
        "src_frame_idx": 150,
        "bbox": [
            543,
            112,
            167,
            219
        ],
        "left_eye": [
            583,
            202
        ],
        "right_eye": [
            662,
            197
        ]
    },
    {
        "frame": 6,
        "src_frame_idx": 180,
        "bbox": [
            545,
            100,
            161,
            229
        ],
        "left_eye": [
            586,
            186
        ],
        "right_eye": [
            666,
            188
        ]
    },
    {
        "frame": 7,
        "src_frame_idx": 210,
        "bbox": [
            567,
            113,
            157,
            217
        ],
        "left_eye": [
            610,
            196
        ],
        "right_eye": [
            684,
            183
        ]
    },
    {
        "frame": 8,
        "src_frame_idx": 240,
        "bbox": [
            538,
            111,
            167,
            221
        ],
        "left_eye": [
            583,
            199
        ],
        "right_eye": [
            663,
            188
        ]
    },
    {
        "frame": 9,
        "src_frame_idx": 270,
        "bbox": [
            535,
            128,
            172,
            222
        ],
        "left_eye": [
            582,
            216
        ],
        "right_eye": [
            659,
            202
        ]
    },
    {
        "frame": 10,
        "src_frame_idx": 300,
        "bbox": [
            545,
            134,
            170,
            217
        ],
        "left_eye": [
            586,
            220
        ],
        "right_eye": [
            665,
            210
        ]
    },
    {
        "frame": 11,
        "src_frame_idx": 330,
        "bbox": [
            552,
            129,
            171,
            220
        ],
        "left_eye": [
            593,
            217
        ],
        "right_eye": [
            671,
            209
        ]
    }
]