[
    {
        "frame": 0,
        "src_frame_idx": 0,
        "bbox": [
            245,
            75,
            108,
            152
        ],
        "left_eye": [
            285,
            138
        ],
        "right_eye": [
            331,
            129
        ]
    },
    {
        "frame": 1,
        "src_frame_idx": 25,
        "bbox": [
            249,
            79,
            109,
            152
        ],
        "left_eye": [
            293,
            144
        ],
        "right_eye": [
            339,
            138
        ]
    },
    {
        "frame": 2,
        "src_frame_idx": 50,
        "bbox": [
            237,
            86,
            110,
            152
        ],
        "left_eye": [
            276,
            149
        ],
        "right_eye": [
            322,
            141
        ]
    },
    {
        "frame": 3,
        "src_frame_idx": 75,
        "bbox": [
            244,
            69,
            108,
            146
        ],
        "left_eye": [
            282,
            128
        ],
        "right_eye": [
            328,
            121
        ]
    },
    {
        "frame": 4,
        "src_frame_idx": 100,
        "bbox": [
            243,
            71,
            112,
            156
        ],
        "left_eye": [
            285,
            134
        ],
        "right_eye": [
            332,
            126
        ]
    },
    {
        "frame": 5,
        "src_frame_idx": 125,
        "bbox": [
            256,
            80,
            103,
            145
        ],
        "left_eye": [
            301,
            136
        ],
        "right_eye": [
            345,
            137
        ]
    },
    {
        "frame": 6,
        "src_frame_idx": 150,
        "bbox": [
            259,
            74,
            104,
            150
        ],
        "left_eye": [
            305,
            133
        ],
        "right_eye": [
            348,
            137
        ]
    },
    {
        "frame": 7,
        "src_frame_idx": 175,
        "bbox": [
            261,
            74,
            107,
            148
        ],
        "left_eye": [
            308,
            134
        ],
        "right_eye": [
            352,
            137
        ]
    },
    {
        "frame": 8,
        "src_frame_idx": 200,
        "bbox": [
            258,
            80,
            105,
            146
        ],
        "left_eye": [
            306,
            138
        ],
        "right_eye": [
            349,
            141
        ]
    },
    {
        "frame": 9,
        "src_frame_idx": 225,
        "bbox": [
            221,
            75,
            115,
            156
        ],
        "left_eye": [
            257,
            139
        ],
        "right_eye": [
            303,
            126
        ]
    },
    {
        "frame": 10,
        "src_frame_idx": 250,
        "bbox": [
            229,
            79,
            109,
            151
        ],
        "left_eye": [
            264,
            139
        ],
        "right_eye": [
            310,
            130
        ]
    },
    {
        "frame": 11,
        "src_frame_idx": 275,
        "bbox": [
            234,
            84,
            114,
            156
        ],
        "left_eye": [
            272,
            148
        ],
        "right_eye": [
            320,
            143
        ]
    },
    {
        "frame": 12,
        "src_frame_idx": 300,
        "bbox": [
            224,
            61,
            114,
            155
        ],
        "left_eye": [
            263,
            126
        ],
        "right_eye": [
            310,
            117
        ]
    },
    {
        "frame": 13,
        "src_frame_idx": 325,
        "bbox": [
            234,
            87,
            107,
            149
        ],
        "left_eye": [
            270,
            147
        ],
        "right_eye": [
            315,
            138
        ]
    },
    {
        "frame": 14,
        "src_frame_idx": 350,
        "bbox": [
            229,
            75,
            110,
            151
        ],
        "left_eye": [
            268,
            139
        ],
        "right_eye": [
            313,
            129
        ]
    },
    {
        "frame": 15,
        "src_frame_idx": 375,
        "bbox": [
            231,
            64,
            110,
            151
        ],
        "left_eye": [
            271,
            130
        ],
        "right_eye": [
            317,
            120
        ]
    },
    {
        "frame": 16,
        "src_frame_idx": 400,
        "bbox": [
            232,
            74,
            111,
            151
        ],
        "left_eye": [
            270,
            137
        ],
        "right_eye": [
            316,
            126
        ]
    }
]