[
    {
        "frame": 0,
        "src_frame_idx": 0,
        "bbox": [
            563,
            122,
            186,
            253
        ],
        "left_eye": [
            600,
            221
        ],
        "right_eye": [
            686,
            214
        ]
    },
    {
        "frame": 1,
        "src_frame_idx": 30,
        "bbox": [
            574,
            104,
            188,
            257
        ],
        "left_eye": [
            605,
            205
        ],
        "right_eye": [
            694,
            197
        ]
    },
    {
        "frame": 2,
        "src_frame_idx": 60,
        "bbox": [
            561,
            114,
            188,
            262
        ],
        "left_eye": [
            600,
            216
        ],
        "right_eye": [
            689,
            212
        ]
    },
    {
        "frame": 3,
        "src_frame_idx": 90,
        "bbox": [
            570,
            120,
            185,
            246
        ],
        "left_eye": [
            609,
            216
        ],
        "right_eye": [
            698,
            210
        ]
    },
    {
        "frame": 4,
        "src_frame_idx": 120,
        "bbox": [
            573,
            115,
            183,
            255
        ],
        "left_eye": [
            609,
            213
        ],
        "right_eye": [
            699,
            209
        ]
    },
    {
        "frame": 5,
        "src_frame_idx": 150,
        "bbox": [
            569,
            100,
            185,
            267
        ],
        "left_eye": [
            611,
            201
        ],
        "right_eye": [
            703,
            194
        ]
    },
    {
        "frame": 6,
        "src_frame_idx": 180,
        "bbox": [
            554,
            113,
            191,
            265
        ],
        "left_eye": [
            593,
            217
        ],
        "right_eye": [
            688,
            210
        ]
    },
    {
        "frame": 7,
        "src_frame_idx": 210,
        "bbox": [
            556,
            107,
            182,
            252
        ],
        "left_eye": [
            593,
            208
        ],
        "right_eye": [
            682,
            201
        ]
    },
    {
        "frame": 8,
        "src_frame_idx": 240,
        "bbox": [
            569,
            99,
            185,
            264
        ],
        "left_eye": [
            604,
            205
        ],
        "right_eye": [
            693,
            200
        ]
    },
    {
        "frame": 9,
        "src_frame_idx": 270,
        "bbox": [
            561,
            116,
            191,
            259
        ],
        "left_eye": [
            602,
            217
        ],
        "right_eye": [
            692,
            211
        ]
    }
]