[
    {
        "frame": 0,
        "src_frame_idx": 0,
        "bbox": [
            135,
            79,
            81,
            109
        ],
        "left_eye": [
            163,
            118
        ],
        "right_eye": [
            199,
            118
        ]
    },
    {
        "frame": 1,
        "src_frame_idx": 30,
        "bbox": [
            138,
            92,
            82,
            99
        ],
        "left_eye": [
            164,
            129
        ],
        "right_eye": [
            201,
            123
        ]
    },
    {
        "frame": 2,
        "src_frame_idx": 60,
        "bbox": [
            141,
            86,
            84,
            111
        ],
        "left_eye": [
            168,
            126
        ],
        "right_eye": [
            206,
            125
        ]
    },
    {
        "frame": 3,
        "src_frame_idx": 90,
        "bbox": [
            400,
            147,
            56,
            68
        ],
        "left_eye": [
            416,
            171
        ],
        "right_eye": [
            443,
            165
        ]
    },
    {
        "frame": 4,
        "src_frame_idx": 120,
        "bbox": [
            143,
            85,
            82,
            106
        ],
        "left_eye": [
            170,
            121
        ],
        "right_eye": [
            208,
            121
        ]
    },
    {
        "frame": 5,
        "src_frame_idx": 150,
        "bbox": [
            133,
            77,
            85,
            104
        ],
        "left_eye": [
            157,
            116
        ],
        "right_eye": [
            196,
            109
        ]
    },
    {
        "frame": 6,
        "src_frame_idx": 180,
        "bbox": [
            146,
            92,
            86,
            108
        ],
        "left_eye": [
            172,
            129
        ],
        "right_eye": [
            211,
            126
        ]
    },
    {
        "frame": 7,
        "src_frame_idx": 210,
        "bbox": [
            147,
            81,
            85,
            109
        ],
        "left_eye": [
            175,
            118
        ],
        "right_eye": [
            213,
            120
        ]
    },
    {
        "frame": 8,
        "src_frame_idx": 240,
        "bbox": [
            151,
            83,
            81,
            104
        ],
        "left_eye": [
            178,
            118
        ],
        "right_eye": [
            216,
            119
        ]
    },
    {
        "frame": 9,
        "src_frame_idx": 270,
        "bbox": [
            151,
            78,
            82,
            109
        ],
        "left_eye": [
            182,
            117
        ],
        "right_eye": [
            219,
            121
        ]
    },
    {
        "frame": 10,
        "src_frame_idx": 300,
        "bbox": [
            149,
            82,
            83,
            109
        ],
        "left_eye": [
            180,
            120
        ],
        "right_eye": [
            215,
            123
        ]
    },
    {
        "frame": 11,
        "src_frame_idx": 330,
        "bbox": [
            150,
            84,
            82,
            111
        ],
        "left_eye": [
            176,
            123
        ],
        "right_eye": [
            214,
            125
        ]
    },
    {
        "frame": 12,
        "src_frame_idx": 360,
        "bbox": [
            147,
            82,
            83,
            108
        ],
        "left_eye": [
            173,
            121
        ],
        "right_eye": [
            213,
            121
        ]
    },
    {
        "frame": 13,
        "src_frame_idx": 390,
        "bbox": [
            152,
            82,
            82,
            109
        ],
        "left_eye": [
            181,
            120
        ],
        "right_eye": [
            219,
            124
        ]
    },
    {
        "frame": 14,
        "src_frame_idx": 420,
        "bbox": [
            151,
            81,
            81,
            109
        ],
        "left_eye": [
            180,
            118
        ],
        "right_eye": [
            217,
            119
        ]
    },
    {
        "frame": 15,
        "src_frame_idx": 450,
        "bbox": [
            146,
            80,
            85,
            110
        ],
        "left_eye": [
            175,
            116
        ],
        "right_eye": [
            214,
            118
        ]
    },
    {
        "frame": 16,
        "src_frame_idx": 480,
        "bbox": [
            151,
            84,
            80,
            109
        ],
        "left_eye": [
            179,
            122
        ],
        "right_eye": [
            215,
            123
        ]
    },
    {
        "frame": 17,
        "src_frame_idx": 510,
        "bbox": [
            146,
            76,
            83,
            110
        ],
        "left_eye": [
            172,
            116
        ],
        "right_eye": [
            210,
            117
        ]
    },
    {
        "frame": 18,
        "src_frame_idx": 540,
        "bbox": [
            154,
            84,
            85,
            110
        ],
        "left_eye": [
            186,
            119
        ],
        "right_eye": [
            224,
            125
        ]
    },
    {
        "frame": 19,
        "src_frame_idx": 570,
        "bbox": [
            154,
            85,
            84,
            110
        ],
        "left_eye": [
            184,
            125
        ],
        "right_eye": [
            221,
            128
        ]
    },
    {
        "frame": 20,
        "src_frame_idx": 600,
        "bbox": [
            157,
            91,
            79,
            103
        ],
        "left_eye": [
            184,
            127
        ],
        "right_eye": [
            220,
            129
        ]
    },
    {
        "frame": 21,
        "src_frame_idx": 630,
        "bbox": [
            149,
            78,
            85,
            115
        ],
        "left_eye": [
            178,
            119
        ],
        "right_eye": [
            216,
            122
        ]
    },
    {
        "frame": 22,
        "src_frame_idx": 660,
        "bbox": [
            151,
            81,
            83,
            111
        ],
        "left_eye": [
            179,
            121
        ],
        "right_eye": [
            216,
            126
        ]
    }
]