[
    {
        "frame": 0,
        "src_frame_idx": 0,
        "bbox": [
            172,
            78,
            157,
            211
        ],
        "left_eye": [
            197,
            173
        ],
        "right_eye": [
            259,
            155
        ]
    },
    {
        "frame": 1,
        "src_frame_idx": 30,
        "bbox": [
            201,
            85,
            161,
            216
        ],
        "left_eye": [
            232,
            177
        ],
        "right_eye": [
            296,
            168
        ]
    },
    {
        "frame": 2,
        "src_frame_idx": 60,
        "bbox": [
            188,
            96,
            173,
            257
        ],
        "left_eye": [
            219,
            194
        ],
        "right_eye": [
            292,
            199
        ]
    },
    {
        "frame": 3,
        "src_frame_idx": 90,
        "bbox": [
            187,
            94,
            164,
            229
        ],
        "left_eye": [
            222,
            186
        ],
        "right_eye": [
            296,
            185
        ]
    },
    {
        "frame": 4,
        "src_frame_idx": 120,
        "bbox": [
            205,
            87,
            163,
            229
        ],
        "left_eye": [
            242,
            179
        ],
        "right_eye": [
            314,
            175
        ]
    },
    {
        "frame": 5,
        "src_frame_idx": 150,
        "bbox": [
            203,
            91,
            167,
            224
        ],
        "left_eye": [
            248,
            176
        ],
        "right_eye": [
            324,
            177
        ]
    },
    {
        "frame": 6,
        "src_frame_idx": 180,
        "bbox": [
            220,
            74,
            163,
            229
        ],
        "left_eye": [
            267,
            163
        ],
        "right_eye": [
            341,
            168
        ]
    },
    {
        "frame": 7,
        "src_frame_idx": 210,
        "bbox": [
            211,
            86,
            164,
            238
        ],
        "left_eye": [
            252,
            176
        ],
        "right_eye": [
            328,
            177
        ]
    },
    {
        "frame": 8,
        "src_frame_idx": 240,
        "bbox": [
            193,
            86,
            164,
            232
        ],
        "left_eye": [
            221,
            177
        ],
        "right_eye": [
            293,
            174
        ]
    },
    {
        "frame": 9,
        "src_frame_idx": 270,
        "bbox": [
            180,
            80,
            178,
            241
        ],
        "left_eye": [
            210,
            180
        ],
        "right_eye": [
            284,
            175
        ]
    },
    {
        "frame": 10,
        "src_frame_idx": 300,
        "bbox": [
            192,
            93,
            166,
            227
        ],
        "left_eye": [
            226,
            189
        ],
        "right_eye": [
            296,
            172
        ]
    },
    {
        "frame": 11,
        "src_frame_idx": 330,
        "bbox": [
            181,
            87,
            177,
            241
        ],
        "left_eye": [
            210,
            190
        ],
        "right_eye": [
            293,
            180
        ]
    }
]