[
    {
        "frame": 0,
        "src_frame_idx": 0,
        "bbox": [
            846,
            160,
            211,
            273
        ],
        "left_eye": [
            897,
            279
        ],
        "right_eye": [
            996,
            268
        ]
    },
    {
        "frame": 1,
        "src_frame_idx": 25,
        "bbox": [
            858,
            143,
            202,
            283
        ],
        "left_eye": [
            908,
            260
        ],
        "right_eye": [
            1007,
            251
        ]
    },
    {
        "frame": 2,
        "src_frame_idx": 50,
        "bbox": [
            788,
            143,
            206,
            275
        ],
        "left_eye": [
            840,
            252
        ],
        "right_eye": [
            940,
            247
        ]
    },
    {
        "frame": 3,
        "src_frame_idx": 75,
        "bbox": [
            790,
            132,
            210,
            285
        ],
        "left_eye": [
            837,
            247
        ],
        "right_eye": [
            941,
            244
        ]
    },
    {
        "frame": 4,
        "src_frame_idx": 100,
        "bbox": [
            297,
            695,
            26,
            33
        ],
        "left_eye": [
            304,
            709
        ],
        "right_eye": [
            315,
            708
        ]
    },
    {
        "frame": 5,
        "src_frame_idx": 125,
        "bbox": [
            872,
            155,
            209,
            281
        ],
        "left_eye": [
            928,
            269
        ],
        "right_eye": [
            1033,
            277
        ]
    },
    {
        "frame": 6,
        "src_frame_idx": 150,
        "bbox": [
            849,
            174,
            208,
            287
        ],
        "left_eye": [
            903,
            290
        ],
        "right_eye": [
            1005,
            296
        ]
    },
    {
        "frame": 7,
        "src_frame_idx": 175,
        "bbox": [
            850,
            152,
            205,
            277
        ],
        "left_eye": [
            900,
            266
        ],
        "right_eye": [
            1001,
            271
        ]
    },
    {
        "frame": 8,
        "src_frame_idx": 200,
        "bbox": [
            843,
            153,
            205,
            273
        ],
        "left_eye": [
            895,
            263
        ],
        "right_eye": [
            993,
            272
        ]
    },
    {
        "frame": 9,
        "src_frame_idx": 225,
        "bbox": [
            869,
            178,
            196,
            265
        ],
        "left_eye": [
            927,
            282
        ],
        "right_eye": [
            1020,
            294
        ]
    },
    {
        "frame": 10,
        "src_frame_idx": 250,
        "bbox": [
            865,
            177,
            198,
            267
        ],
        "left_eye": [
            928,
            281
        ],
        "right_eye": [
            1020,
            294
        ]
    },
    {
        "frame": 11,
        "src_frame_idx": 275,
        "bbox": [
            858,
            161,
            207,
            277
        ],
        "left_eye": [
            920,
            270
        ],
        "right_eye": [
            1017,
            283
        ]
    },
    {
        "frame": 12,
        "src_frame_idx": 300,
        "bbox": [
            861,
            153,
            208,
            270
        ],
        "left_eye": [
            919,
            259
        ],
        "right_eye": [
            1017,
            269
        ]
    }
]